{
  "bot_description": "🤖 Бот ГО «Ф1» - це канал звʼязку з нашою командою.\n\nЧерез бота ви можете залишити звернення, обрати тему (категорію) та, за бажанням, надіслати повідомлення анонімно.\n\nМи працюємо з повагою, конфіденційністю та без осуду.",
  "ngo_info": "ГО «Ф1» - всеукраїнське громадське обʼєднання, яке підтримує жінок, ВПО, дітей та інші вразливі групи.\n\nНапрями: протидія насильству і булінгу, психологічна та правова підтримка, навчання і перекваліфікація, гуманітарна допомога, розвиток громад.\n\nАдреса простору SkillsLab_F1: м. Одеса, Французький бульвар, 7, офіс 5.",
  "ngo_mission": "Місія ГО «Ф1» - створювати безпечний простір для розвитку, взаємодії та самореалізації жінок, сприяти гендерній рівності, підтримувати людей у кризових ситуаціях та розбудовувати справедливе, інклюзивне суспільство.",
  "ngo_directions": "Напрями діяльності ГО «Ф1»:\n- превенція та протидія гендерно зумовленому і домашньому насильству\n- психосоціальна підтримка та психологічна допомога\n- протидія булінгу\n- навчання та перекваліфікація (цифрова грамотність, працевлаштування)\n- підтримка ВПО та вразливих груп\n- розвиток громад та жіночих ініціатив\n- гуманітарна допомога та відновлення\n- охорона здоровʼя, захист материнства та дитинства\n- міжнародна співпраця",
  "ngo_contacts": "Контакти ГО «Ф1»:\n- Адреса простору SkillsLab_F1: м. Одеса, Французький бульвар, 7, офіс 5\n- Президентка: Гришкова Катерина, тел. +380506631331, email 6631331@gmail.com\n- Офіційний домен пошти: ngof1.org"
}